{
    "name": "expension:end_laboratory_side",
    "fallback": "minecraft:empty",
    "elements": [
      {
        "weight": 2,
        "element": {
          "location": "expension:end_laboratory/side/amethyst",
          "processors": "minecraft:empty",
          "projection": "rigid",
          "element_type": "minecraft:single_pool_element"
        }
      },
      {
        "weight": 2,
        "element": {
          "location": "expension:end_laboratory/side/amethyst_reversed",
          "processors": "minecraft:empty",
          "projection": "rigid",
          "element_type": "minecraft:single_pool_element"
        }
      },
      {
        "weight": 2,
        "element": {
          "location": "expension:end_laboratory/side/creeper",
          "processors": "minecraft:empty",
          "projection": "rigid",
          "element_type": "minecraft:single_pool_element"
        }
      },
      {
        "weight": 2,
        "element": {
          "location": "expension:end_laboratory/side/creeper_reversed",
          "processors": "minecraft:empty",
          "projection": "rigid",
          "element_type": "minecraft:single_pool_element"
        }
      },
      {
        "weight": 2,
        "element": {
          "location": "expension:end_laboratory/side/hajimi",
          "processors": "minecraft:empty",
          "projection": "rigid",
          "element_type": "minecraft:single_pool_element"
        }
      },
      {
        "weight": 12,
        "element": {
          "location": "expension:end_laboratory/side/magma",
          "processors": "minecraft:empty",
          "projection": "rigid",
          "element_type": "minecraft:single_pool_element"
        }
      },
      {
        "weight": 6,
        "element": {
          "location": "expension:end_laboratory/side/portal",
          "processors": "minecraft:empty",
          "projection": "rigid",
          "element_type": "minecraft:single_pool_element"
        }
      },
      {
        "weight": 12,
        "element": {
          "location": "expension:end_laboratory/side/trap",
          "processors": "minecraft:empty",
          "projection": "rigid",
          "element_type": "minecraft:single_pool_element"
        }
      },
      {
        "weight": 12,
        "element": {
          "location": "expension:end_laboratory/side/warehouse",
          "processors": "minecraft:empty",
          "projection": "rigid",
          "element_type": "minecraft:single_pool_element"
        }
      },
      {
        "weight": 3,
        "element": {
          "location": "expension:end_laboratory/side/spider_single",
          "processors": "minecraft:empty",
          "projection": "rigid",
          "element_type": "minecraft:single_pool_element"
        }
      },
      {
        "weight": 3,
        "element": {
          "location": "expension:end_laboratory/side/spiders",
          "processors": "minecraft:empty",
          "projection": "rigid",
          "element_type": "minecraft:single_pool_element"
        }
      }
    ]
}